pyqueue_client/__init__.py
pyqueue_client/config.py
pyqueue_client/queue_manager.py
pyqueue_client/remote_queue.py
pyqueue_client-1.2.1.dist-info/licenses/LICENSE
pyqueue_client-1.2.1.dist-info/METADATA
pyqueue_client-1.2.1.dist-info/WHEEL
pyqueue_client-1.2.1.dist-info/top_level.txt
pyqueue_client-1.2.1.dist-info/RECORD
