Metadata-Version: 2.4
Name: pyqueue-client
Version: 1.2.1
Summary: Python client library for adding messages to PyQueue with local and remote support
Home-page: https://github.com/downlevel/pyqueue-client
Author: Mauro Giulivi
Classifier: Programming Language :: Python :: 3
Classifier: License :: OSI Approved :: MIT License
Classifier: Operating System :: OS Independent
Requires-Python: >=3.6
License-File: LICENSE
Requires-Dist: requests>=2.25.0
Requires-Dist: urllib3>=1.26.0
Dynamic: author
Dynamic: classifier
Dynamic: description
Dynamic: description-content-type
Dynamic: home-page
Dynamic: license-file
Dynamic: requires-dist
Dynamic: requires-python
Dynamic: summary
